piscada_cloud/__init__.py
piscada_cloud/auth.py
piscada_cloud/cloud_functions.py
piscada_cloud/data.py
piscada_cloud/legacy/__init__.py
piscada_cloud/legacy/results.py
piscada_cloud/manipulations.py
piscada_cloud/mappings.py
piscada_cloud/meta_data.py
piscada_cloud-7.1.0.dist-info/LICENSE
piscada_cloud-7.1.0.dist-info/METADATA
piscada_cloud-7.1.0.dist-info/WHEEL
piscada_cloud-7.1.0.dist-info/RECORD
