Metadata-Version: 2.1
Name: piscada_cloud
Version: 7.1.0
Summary: Library for the Piscada Cloud including authentication and data access.
Home-page: https://piscada.com/
License: Other/Proprietary License
Keywords: piscada,automation,building-automation,fish-farming,assisted-living
Author: Tim Jagenberg
Author-email: tim.jagenberg@piscada.com
Requires-Python: >=3.10,<4.0
Classifier: Development Status :: 4 - Beta
Classifier: Intended Audience :: Developers
Classifier: License :: Other/Proprietary License
Classifier: Programming Language :: Python :: 3
Classifier: Programming Language :: Python :: 3.10
Classifier: Programming Language :: Python :: 3.11
Classifier: Programming Language :: Python :: 3.12
Classifier: Topic :: Scientific/Engineering
Classifier: Topic :: Software Development
Requires-Dist: numpy (>=1.26.2,<2.0.0)
Requires-Dist: pandas (>=2.1.3,<3.0.0)
Requires-Dist: pyarrow (>=14.0.1,<15.0.0)
Requires-Dist: requests (>=2.31.0,<3.0.0)
Requires-Dist: toml (>=0.10.2,<0.11.0)
